oxvox-0.7.2.dist-info/METADATA
oxvox-0.7.2.dist-info/WHEEL
oxvox-0.7.2.dist-info/licenses/LICENSE
oxvox/indexing.py
oxvox/py.typed
oxvox/util.py
oxvox/tests/test_ox_vox_nns.py
oxvox/tests/test_oxvox_indexing.py
oxvox/nns.py
oxvox/__init__.py
oxvox/_oxvox.pypy310-pp73-aarch64-linux-gnu.so
oxvox-0.7.2.dist-info/RECORD
