Metadata-Version: 2.4
Name: oxvox
Version: 0.7.2
Classifier: Programming Language :: Rust
Classifier: Programming Language :: Python :: Implementation :: CPython
Classifier: Programming Language :: Python :: Implementation :: PyPy
Requires-Dist: numpy
Requires-Dist: numpy-indexed
Requires-Dist: pytest
License-File: LICENSE
Summary: Performant operations on array & pointcloud data, written in Rust
Keywords: nearest,neighbour,pointcloud,array,ndarray,python
Author: Hamish Morgan <ham430@gmail.com>
Author-email: Hamish Morgan <ham430@gmail.com>
Requires-Python: >=3.8
Project-URL: Source Code, https://github.com/hacmorgan/oxvox
